CHANGELOG.md
LICENSE
MANIFEST.in
README.md
setup.py
lib/__init__.py
sarpoka.egg-info/PKG-INFO
sarpoka.egg-info/SOURCES.txt
sarpoka.egg-info/dependency_links.txt
sarpoka.egg-info/requires.txt
sarpoka.egg-info/top_level.txt
tests/__init__.py
tests/test_utility_units.py
utils/__init__.py
utils/generics.py
utils/parsers.py